cosmic_ray_parallel/__init__.py
cosmic_ray_parallel/engine.py
cosmic_ray_parallel/version.py
cosmic_ray_parallel-1.0.1.dist-info/DESCRIPTION.rst
cosmic_ray_parallel-1.0.1.dist-info/METADATA
cosmic_ray_parallel-1.0.1.dist-info/RECORD
cosmic_ray_parallel-1.0.1.dist-info/WHEEL
cosmic_ray_parallel-1.0.1.dist-info/entry_points.txt
cosmic_ray_parallel-1.0.1.dist-info/metadata.json
cosmic_ray_parallel-1.0.1.dist-info/top_level.txt
