Metadata-Version: 2.0
Name: cosmic-ray-parallel
Version: 1.0.1
Summary: Pytest test-runner plugin for Cosmic Ray
Home-page: https://github.com/franzhaas/cosmic_ray_parallel
Author: Franz Haas
Author-email: UNKNOWN
License: MIT
Keywords: testing
Platform: any
Classifier: Development Status :: 4 - Beta
Classifier: Environment :: Console
Classifier: Intended Audience :: Developers
Classifier: License :: OSI Approved :: MIT License
Classifier: Operating System :: OS Independent
Classifier: Programming Language :: Python
Classifier: Programming Language :: Python :: 3.4
Classifier: Programming Language :: Python :: 3.5
Classifier: Programming Language :: Python :: 3.6
Classifier: Topic :: Software Development :: Libraries :: Python Modules
Classifier: Topic :: Software Development :: Testing
